addroot/__init__.py
addroot/_modidx.py
addroot/addgitroot.py
addroot-0.1.0.dist-info/LICENSE
addroot-0.1.0.dist-info/METADATA
addroot-0.1.0.dist-info/WHEEL
addroot-0.1.0.dist-info/entry_points.txt
addroot-0.1.0.dist-info/top_level.txt
addroot-0.1.0.dist-info/RECORD
